odoo/addons/payment_partner/README.rst
odoo/addons/payment_partner/__init__.py
odoo/addons/payment_partner/__manifest__.py
odoo/addons/payment_partner/i18n/it.po
odoo/addons/payment_partner/i18n/payment_partner.pot
odoo/addons/payment_partner/models/__init__.py
odoo/addons/payment_partner/models/payment_provider.py
odoo/addons/payment_partner/readme/CONTRIBUTORS.md
odoo/addons/payment_partner/readme/DESCRIPTION.md
odoo/addons/payment_partner/readme/USAGE.md
odoo/addons/payment_partner/static/description/icon.png
odoo/addons/payment_partner/static/description/index.html
odoo/addons/payment_partner/tests/__init__.py
odoo/addons/payment_partner/tests/test_payment_partner.py
odoo/addons/payment_partner/views/payment_provider.xml
odoo_addon_payment_partner-16.0.1.0.0.3.dist-info/METADATA
odoo_addon_payment_partner-16.0.1.0.0.3.dist-info/WHEEL
odoo_addon_payment_partner-16.0.1.0.0.3.dist-info/top_level.txt
odoo_addon_payment_partner-16.0.1.0.0.3.dist-info/RECORD
